MANIFEST.in
README
setup.py
bin/cis
bin/cis.lsf
jasmin_cis/__init__.py
jasmin_cis/cis.py
jasmin_cis/col.py
jasmin_cis/col_framework.py
jasmin_cis/col_implementations.py
jasmin_cis/data_index.py
jasmin_cis/evaluate.py
jasmin_cis/exceptions.py
jasmin_cis/find.py
jasmin_cis/haversinedistancekdtreeindex.py
jasmin_cis/info.py
jasmin_cis/kdtree.py
jasmin_cis/logging.conf
jasmin_cis/parse.py
jasmin_cis/parse_datetime.py
jasmin_cis/plugin.py
jasmin_cis/stats.py
jasmin_cis/time_util.py
jasmin_cis/utils.py
jasmin_cis.egg-info/PKG-INFO
jasmin_cis.egg-info/SOURCES.txt
jasmin_cis.egg-info/dependency_links.txt
jasmin_cis.egg-info/requires.txt
jasmin_cis.egg-info/top_level.txt
jasmin_cis/aggregation/__init__.py
jasmin_cis/aggregation/aggregate.py
jasmin_cis/aggregation/aggregation_grid.py
jasmin_cis/aggregation/aggregation_kernels.py
jasmin_cis/aggregation/aggregator.py
jasmin_cis/data_io/Coord.py
jasmin_cis/data_io/__init__.py
jasmin_cis/data_io/aeronet.py
jasmin_cis/data_io/common_data.py
jasmin_cis/data_io/data_reader.py
jasmin_cis/data_io/data_writer.py
jasmin_cis/data_io/gridded_data.py
jasmin_cis/data_io/hdf.py
jasmin_cis/data_io/hdf_sd.py
jasmin_cis/data_io/hdf_vd.py
jasmin_cis/data_io/hyperpoint.py
jasmin_cis/data_io/hyperpoint_view.py
jasmin_cis/data_io/netcdf.py
jasmin_cis/data_io/read.py
jasmin_cis/data_io/ungridded_data.py
jasmin_cis/data_io/write_hdf.py
jasmin_cis/data_io/write_netcdf.py
jasmin_cis/data_io/products/AProduct.py
jasmin_cis/data_io/products/CCI.py
jasmin_cis/data_io/products/MODIS.py
jasmin_cis/data_io/products/NCAR_NetCDF_RAF.py
jasmin_cis/data_io/products/__init__.py
jasmin_cis/data_io/products/abstract_NetCDF_CF.py
jasmin_cis/data_io/products/caliop.py
jasmin_cis/data_io/products/products.py
jasmin_cis/plotting/__init__.py
jasmin_cis/plotting/comparative_scatter.py
jasmin_cis/plotting/contour_plot.py
jasmin_cis/plotting/contourf_plot.py
jasmin_cis/plotting/formatter.py
jasmin_cis/plotting/generic_plot.py
jasmin_cis/plotting/heatmap.py
jasmin_cis/plotting/histogram2d.py
jasmin_cis/plotting/histogram3d.py
jasmin_cis/plotting/line_plot.py
jasmin_cis/plotting/overlay.py
jasmin_cis/plotting/plot.py
