Metadata-Version: 1.1
Name: jasmin-cis
Version: 1.0.0
Summary: JASMIN Community Inter-comparison Suite
Home-page: http://proj.badc.rl.ac.uk/cedaservices/wiki/JASMIN/CommunityIntercomparisonSuite
Author: Philip Kershaw
Author-email: Philip.Kershaw@stfc.ac.uk
License: UNKNOWN
Platform: UNKNOWN
Classifier: License :: OSI Approved :: GNU Lesser General Public License v3 or later (LGPLv3+)
Classifier: Topic :: Scientific/Engineering :: Atmospheric Science
Classifier: Topic :: Scientific/Engineering :: Visualization
Classifier: Environment :: Console
